writefreely_mcp_server/__init__.py
writefreely_mcp_server/api_client.py
writefreely_mcp_server/config.py
writefreely_mcp_server/server.py
writefreely_mcp_server/tools/__init__.py
writefreely_mcp_server/tools/auth.py
writefreely_mcp_server/tools/collections.py
writefreely_mcp_server/tools/feed.py
writefreely_mcp_server/tools/posts.py
writefreely_mcp_server-0.1.3.dist-info/METADATA
writefreely_mcp_server-0.1.3.dist-info/WHEEL
writefreely_mcp_server-0.1.3.dist-info/entry_points.txt
writefreely_mcp_server-0.1.3.dist-info/licenses/LICENSE
writefreely_mcp_server-0.1.3.dist-info/RECORD
