Metadata-Version: 2.4
Name: writefreely-mcp-server
Version: 0.1.3
Summary: An MCP server for interacting with WriteFreely API, enabling AI agents like Claude to perform blogging actions. Supports both self-hosted WriteFreely instances and the Write.as hosted service. This is a community-built, independent project.
Project-URL: Homepage, https://github.com/laxmena/writefreely-mcp-server
Project-URL: Repository, https://github.com/laxmena/writefreely-mcp-server.git
Project-URL: Documentation, https://github.com/laxmena/writefreely-mcp-server#readme
Project-URL: Issues, https://github.com/laxmena/writefreely-mcp-server/issues
Author: Lakshmanan Meiyappan
License-Expression: MIT
License-File: LICENSE
Keywords: ai-agent,api,blogging,mcp,writefreely
Classifier: Development Status :: 3 - Alpha
Classifier: Intended Audience :: Developers
Classifier: License :: OSI Approved :: MIT License
Classifier: Programming Language :: Python :: 3
Classifier: Programming Language :: Python :: 3.10
Classifier: Programming Language :: Python :: 3.11
Classifier: Programming Language :: Python :: 3.12
Classifier: Programming Language :: Python :: 3.13
Classifier: Topic :: Software Development :: Libraries :: Python Modules
Requires-Python: >=3.10
Requires-Dist: httpx>=0.28.1
Requires-Dist: mcp[cli]>=1.25.0
Requires-Dist: pydantic>=2.12.5
Requires-Dist: python-dotenv>=1.0.1
Provides-Extra: dev
Requires-Dist: mypy>=1.12.0; extra == 'dev'
Requires-Dist: pre-commit>=4.0.1; extra == 'dev'
Requires-Dist: pytest-asyncio>=0.24.0; extra == 'dev'
Requires-Dist: pytest-httpx>=0.30.0; extra == 'dev'
Requires-Dist: pytest>=8.3.3; extra == 'dev'
Requires-Dist: ruff>=0.6.9; extra == 'dev'
